painless_redirects/__init__.py
painless_redirects/admin.py
painless_redirects/conf.py
painless_redirects/managers.py
painless_redirects/middleware-legacy-dry.py
painless_redirects/middleware.py
painless_redirects/models.py
painless_redirects/contrib/djangocms_autoredirect/__init__.py
painless_redirects/contrib/djangocms_autoredirect/models.py
painless_redirects/contrib/filer_autoredirect/.empty
painless_redirects/contrib/folderless_autoredirect/.empty
painless_redirects/locale/de/LC_MESSAGES/django.po
painless_redirects/locale/en/LC_MESSAGES/django.po
painless_redirects/locale/fr/LC_MESSAGES/django.po
painless_redirects/management/__init__.py
painless_redirects/management/commands/__init__.py
painless_redirects/management/commands/painless_redirects_ensure_unique.py
painless_redirects/migrations/0001_initial.py
painless_redirects/migrations/0002_auto_20170803_0402.py
painless_redirects/migrations/0003_auto_20180430_0559.py
painless_redirects/migrations/0004_auto_20180830_0209.py
painless_redirects/migrations/0005_redirect_permanent.py
painless_redirects/migrations/0006_auto_20180830_0219.py
painless_redirects/migrations/0007_auto_20181107_0207.py
painless_redirects/migrations/0008_auto_20191213_0640.py
painless_redirects/migrations/0009_redirect_enabled.py
painless_redirects/migrations/0010_auto_20191213_0650.py
painless_redirects/migrations/0011_auto_20200420_0836.py
painless_redirects/migrations/0012_redirecthit.py
painless_redirects/migrations/0013_auto_20201120_0911.py
painless_redirects/migrations/0014_redirect_ignored.py
painless_redirects/migrations/0015_auto_20210123_0506.py
painless_redirects/migrations/0016_auto_20210223_0518.py
painless_redirects/migrations/__init__.py
painless_redirects/south_migrations/0001_initial.py
painless_redirects/south_migrations/0002_auto__add_field_redirect_wildcard_match__chg_field_redirect_domain__ch.py
painless_redirects/south_migrations/0003_auto__chg_field_redirect_new_path__chg_field_redirect_old_path.py
django_painless_redirects-0.7.1.dist-info/AUTHORS
django_painless_redirects-0.7.1.dist-info/LICENSE
django_painless_redirects-0.7.1.dist-info/METADATA
django_painless_redirects-0.7.1.dist-info/WHEEL
django_painless_redirects-0.7.1.dist-info/top_level.txt
django_painless_redirects-0.7.1.dist-info/RECORD
