Metadata-Version: 2.1
Name: django-painless-redirects
Version: 0.7.1
Summary: Like django.contrib.redirects on steroids. Maybe.
Home-page: https://github.com/bnzk/django-painless-redirects
Author: Ben Stähli
Author-email: bnzk@bnzk.ch
License: The MIT License
Keywords: django,redirect
Platform: OS Independent
License-File: LICENSE
License-File: AUTHORS
Requires-Dist: django
